cameracv2/__init__.py
cameracv2-0.1.dist-info/LICENSES.txt
cameracv2-0.1.dist-info/METADATA
cameracv2-0.1.dist-info/WHEEL
cameracv2-0.1.dist-info/top_level.txt
cameracv2-0.1.dist-info/RECORD
