Metadata-Version: 2.1
Name: cameracv2
Version: 0.1
Summary: This tool was made so that if you are working with cv2 and you want to use the camera you does not need to write that much code just import this pac
Author: Muhammed Yusuf
Author-email: farsanafarooq@gmail.com
Classifier: Programming Language :: Python :: 3
Classifier: License :: OSI Approved :: MIT License
Classifier: Operating System :: OS Independent
License-File: LICENSES.txt
